{
  "videoFile": "/Users/maximovchinnikov/github/ugc-cli/workspace/references/fluently-jess/reels/DWNGoldjBmO.mp4",
  "videoName": "DWNGoldjBmO",
  "analyzedAt": "2026-03-30T06:25:00.136Z",
  "meta": {
    "duration": 62.7,
    "resolution": "720x1280",
    "width": 720,
    "height": 1280,
    "aspectRatio": "9:16",
    "fps": "30/1"
  },
  "transcript": {
    "text": "minute minute base base lead lead object object bow bow row row content content tear tear live live close close wind wind The biggest lie about learning English that you need more vocabulary, you don't. You need to start speaking. Stacy, what advice would you give to a beginner who wants to improve their English quickly? Just talk to me every day. Daily practice with AI tutors works wonders. That's why fluently works. It's like a speaking partner in your pocket. Stop learning English. Start speaking with fluently app.",
    "segments": [
      {
        "start": 0,
        "end": 0.38,
        "text": "minute"
      },
      {
        "start": 0.92,
        "end": 1.38,
        "text": "minute."
      },
      {
        "start": 2.06,
        "end": 2.46,
        "text": "base"
      },
      {
        "start": 3.06,
        "end": 3.46,
        "text": "base,"
      },
      {
        "start": 4.06,
        "end": 4.36,
        "text": "lead"
      },
      {
        "start": 5.26,
        "end": 5.56,
        "text": "lead."
      },
      {
        "start": 6.16,
        "end": 6.56,
        "text": "object"
      },
      {
        "start": 7.26,
        "end": 7.76,
        "text": "object."
      },
      {
        "start": 8.46,
        "end": 8.76,
        "text": "bow"
      },
      {
        "start": 9.46,
        "end": 9.76,
        "text": "bow."
      },
      {
        "start": 10.46,
        "end": 10.76,
        "text": "row"
      },
      {
        "start": 11.46,
        "end": 11.76,
        "text": "row."
      },
      {
        "start": 12.46,
        "end": 12.96,
        "text": "content"
      },
      {
        "start": 13.66,
        "end": 14.16,
        "text": "content."
      },
      {
        "start": 14.86,
        "end": 15.16,
        "text": "tear"
      },
      {
        "start": 15.96,
        "end": 16.26,
        "text": "tear."
      },
      {
        "start": 16.96,
        "end": 17.26,
        "text": "live"
      },
      {
        "start": 18.06,
        "end": 18.36,
        "text": "live."
      },
      {
        "start": 19.06,
        "end": 19.46,
        "text": "close"
      },
      {
        "start": 20.16,
        "end": 20.56,
        "text": "close."
      },
      {
        "start": 21.26,
        "end": 21.56,
        "text": "wind"
      },
      {
        "start": 22.26,
        "end": 22.66,
        "text": "wind."
      },
      {
        "start": 22.96,
        "end": 25.06,
        "text": "The biggest lie about learning English?"
      },
      {
        "start": 25.66,
        "end": 27.26,
        "text": "that you need more vocabulary?"
      },
      {
        "start": 27.56,
        "end": 27.96,
        "text": "You don't."
      },
      {
        "start": 28.76,
        "end": 30.06,
        "text": "You need to start speaking."
      },
      {
        "start": 30.26,
        "end": 34.96,
        "text": "Stacy, what advice would you give to a beginner who wants to improve their English quickly?"
      },
      {
        "start": 35.16,
        "end": 36.76,
        "text": "Just talk to me every day."
      },
      {
        "start": 36.96,
        "end": 39.46,
        "text": "Daily practice with AI tutors works wonders."
      },
      {
        "start": 39.66,
        "end": 41.26,
        "text": "That's why fluently works."
      },
      {
        "start": 41.86,
        "end": 44.26,
        "text": "It's like a speaking partner in your pocket."
      },
      {
        "start": 44.46,
        "end": 46.06,
        "text": "Stop learning English."
      },
      {
        "start": 46.96,
        "end": 49.66,
        "text": "Start speaking with fluently app."
      }
    ]
  },
  "analysis": {
    "summary": "This video uses a common linguistic challenge – homographs (words spelled the same but with different meanings and often pronunciations) – to hook viewers, then transitions into a direct advertisement for an AI English tutoring app called Fluently. The initial segment taps into the shared experience of English learners struggling with such nuances, creating an 'aha moment' of recognition. The video then pivots to offer a solution, positioning the app as a practical tool for improving speaking skills, which is often perceived as the most challenging aspect of language learning. The creator leverages a relatable problem to introduce a product, making the ad feel less intrusive and more like a helpful recommendation.",
    "category": "educational",
    "language": "en",
    "contentAnalysis": {
      "topic": "English language learning, homographs, AI tutoring app promotion",
      "creatorRole": "English language influencer/educator (or portraying one for the ad)",
      "narrativeArc": "The video starts with a linguistic challenge (homographs) to engage the audience, then identifies a common misconception about English learning (vocabulary vs. speaking), introduces an AI tutor as a solution, and finally promotes the Fluently app as the specific tool.",
      "culturalReferences": [],
      "musicIdentification": "unidentified",
      "spokenContent": "The video begins with the creator speaking pairs of homographs (e.g., 'minute' as in time and 'minute' as in small) to highlight the complexities of English pronunciation and meaning. She then states that the biggest lie about learning English is needing more vocabulary, asserting that speaking practice is more crucial. She introduces an AI tutor concept and specifically promotes the 'Fluently' app as a speaking partner.",
      "textOnScreen": [
        "Minute",
        "Minute",
        "Bass",
        "Bass",
        "Lead",
        "Lead",
        "Object",
        "Object",
        "Bow",
        "Bow",
        "Row",
        "Row",
        "Content",
        "Content",
        "Tear",
        "Tear",
        "Live",
        "Live",
        "Close",
        "Close",
        "Wind",
        "Wind",
        "The biggest lie about learning English?",
        "That you need more vocabulary?",
        "You don't.",
        "You need to start speaking.",
        "Stacy, what advice would you give to a beginner who wants to improve their English quickly?",
        "Just talk to me every day.",
        "Daily practice with AI tutors works wonders.",
        "That's why Fluently works.",
        "It's like a speaking partner in your pocket.",
        "Stop learning English.",
        "Start speaking with Fluently app."
      ],
      "keyMoment": "The transition from identifying the problem (homographs) to stating the 'biggest lie about learning English' at 0:23, which directly leads into the solution.",
      "emotionalJourney": "Curiosity (what's the challenge?) → Recognition/Frustration (I know these struggles!) → Relief/Hope (there's a better way!) → Interest (tell me more about this solution)."
    },
    "format": {
      "type": "talking-head",
      "aspectRatio": "9:16",
      "duration": 62.7,
      "hasSubtitles": true,
      "subtitleStyle": "White text with black outline, appearing dynamically as spoken, often with emphasis on key phrases.",
      "hasFaceCam": true,
      "isAIGenerated": false
    },
    "hook": {
      "type": "curiosity-gap",
      "text": "The rapid-fire presentation of homographs like 'Minute' (time) vs. 'Minute' (small) with accompanying images.",
      "whyItWorks": "It immediately engages anyone who has struggled with English pronunciation or meaning, creating a sense of shared experience and curiosity about what the video will reveal about these linguistic quirks. It's a pattern interrupt that quickly establishes the video's relevance to English learners."
    },
    "scenes": [
      {
        "timestamp": "0:00-0:03",
        "type": "hook",
        "description": "A young woman sits facing the camera. Two images appear above her head, one of a tomato timer and one of a small bird, both labeled 'Minute'. She pronounces the word 'minute' in two different ways.",
        "textOnScreen": "Minute, Minute",
        "spokenWords": "minute, minute.",
        "transition": "none",
        "cameraAngle": "medium",
        "emotionalBeat": "Curiosity, recognition for English learners."
      },
      {
        "timestamp": "0:03-0:05",
        "type": "content",
        "description": "The woman continues, with images of a fish (bass) and a bass guitar appearing, both labeled 'Bass'. She pronounces 'bass' in two ways.",
        "textOnScreen": "Bass, Bass",
        "spokenWords": "base, base,",
        "transition": "cut",
        "cameraAngle": "medium",
        "emotionalBeat": "Continued engagement, slight challenge."
      },
      {
        "timestamp": "0:05-0:07",
        "type": "content",
        "description": "Images of a business meeting (lead) and a piece of lead metal appear, labeled 'Lead'. She pronounces 'lead' in two ways.",
        "textOnScreen": "Lead, Lead",
        "spokenWords": "lead, lead.",
        "transition": "cut",
        "cameraAngle": "medium",
        "emotionalBeat": "Reinforcement of the linguistic challenge."
      },
      {
        "timestamp": "0:07-0:09",
        "type": "content",
        "description": "Images of various small objects (object) and people arguing (object) appear, labeled 'Object'. She pronounces 'object' in two ways.",
        "textOnScreen": "Object, Object",
        "spokenWords": "object, object.",
        "transition": "cut",
        "cameraAngle": "medium",
        "emotionalBeat": "Further demonstration of English complexity."
      },
      {
        "timestamp": "0:09-0:11",
        "type": "content",
        "description": "Images of a hair bow (bow) and people bowing (bow) appear, labeled 'Bow'. She pronounces 'bow' in two ways.",
        "textOnScreen": "Bow, Bow",
        "spokenWords": "bow, bow.",
        "transition": "cut",
        "cameraAngle": "medium",
        "emotionalBeat": "Building on the pattern, maintaining interest."
      },
      {
        "timestamp": "0:11-0:13",
        "type": "content",
        "description": "Images of rubber ducks in a row (row) and people arguing (row) appear, labeled 'Row'. She pronounces 'row' in two ways.",
        "textOnScreen": "Row, Row",
        "spokenWords": "row, row.",
        "transition": "cut",
        "cameraAngle": "medium",
        "emotionalBeat": "Continuing the linguistic puzzle."
      },
      {
        "timestamp": "0:13-0:15",
        "type": "content",
        "description": "Images related to digital content (content) and a happy person (content) appear, labeled 'Content'. She pronounces 'content' in two ways.",
        "textOnScreen": "Content, Content",
        "spokenWords": "content, content.",
        "transition": "cut",
        "cameraAngle": "medium",
        "emotionalBeat": "Highlighting more common homographs."
      },
      {
        "timestamp": "0:15-0:17",
        "type": "content",
        "description": "Images of a crying eye (tear) and hands tearing paper (tear) appear, labeled 'Tear'. She pronounces 'tear' in two ways.",
        "textOnScreen": "Tear, Tear",
        "spokenWords": "tear, tear.",
        "transition": "cut",
        "cameraAngle": "medium",
        "emotionalBeat": "Relatability for those learning English."
      },
      {
        "timestamp": "0:17-0:19",
        "type": "content",
        "description": "Images of a family (live) and a news anchor (live) appear, labeled 'Live'. She pronounces 'live' in two ways.",
        "textOnScreen": "Live, Live",
        "spokenWords": "live, live.",
        "transition": "cut",
        "cameraAngle": "medium",
        "emotionalBeat": "Further illustrating the challenge."
      },
      {
        "timestamp": "0:19-0:21",
        "type": "content",
        "description": "Images of a person closing a door (close) and a couple embracing (close) appear, labeled 'Close'. She pronounces 'close' in two ways.",
        "textOnScreen": "Close, Close",
        "spokenWords": "close, close.",
        "transition": "cut",
        "cameraAngle": "medium",
        "emotionalBeat": "Maintaining the pattern."
      },
      {
        "timestamp": "0:21-0:23",
        "type": "content",
        "description": "Images of a windy scene (wind) and a person winding an alarm clock (wind) appear, labeled 'Wind'. She pronounces 'wind' in two ways.",
        "textOnScreen": "Wind, Wind",
        "spokenWords": "wind, wind.",
        "transition": "cut",
        "cameraAngle": "medium",
        "emotionalBeat": "Final example before the pivot."
      },
      {
        "timestamp": "0:23-0:28",
        "type": "content",
        "description": "The woman looks directly at the camera, speaking more assertively. Text overlays appear, stating 'The biggest lie about learning English? That you need more vocabulary? You don't.'",
        "textOnScreen": "The biggest lie about learning English? That you need more vocabulary? You don't.",
        "spokenWords": "The biggest lie about learning English? that you need more vocabulary? You don't.",
        "transition": "cut",
        "cameraAngle": "medium",
        "emotionalBeat": "Intrigue, challenge to common belief."
      },
      {
        "timestamp": "0:28-0:30",
        "type": "content",
        "description": "She continues speaking, with the text 'You need to start speaking.' appearing.",
        "textOnScreen": "You need to start speaking.",
        "spokenWords": "You need to start speaking.",
        "transition": "cut",
        "cameraAngle": "medium",
        "emotionalBeat": "Empowerment, clear direction."
      },
      {
        "timestamp": "0:30-0:35",
        "type": "content",
        "description": "She shifts her gaze slightly, as if addressing someone, and asks, 'Stacy, what advice would you give to a beginner who wants to improve their English quickly?' This is a rhetorical setup for the next part.",
        "textOnScreen": "Stacy, what advice would you give to a beginner who wants to improve their English quickly?",
        "spokenWords": "Stacy, what advice would you give to a beginner who wants to improve their English quickly?",
        "transition": "cut",
        "cameraAngle": "medium",
        "emotionalBeat": "Anticipation for a solution."
      },
      {
        "timestamp": "0:35-0:36",
        "type": "content",
        "description": "She answers her own question, 'Just talk to me every day.'",
        "textOnScreen": "Just talk to me every day.",
        "spokenWords": "Just talk to me every day.",
        "transition": "cut",
        "cameraAngle": "medium",
        "emotionalBeat": "Simple, actionable advice."
      },
      {
        "timestamp": "0:36-0:39",
        "type": "content",
        "description": "She explains, 'Daily practice with AI tutors works wonders.'",
        "textOnScreen": "Daily practice with AI tutors works wonders.",
        "spokenWords": "Daily practice with AI tutors works wonders.",
        "transition": "cut",
        "cameraAngle": "medium",
        "emotionalBeat": "Introduction of the solution type."
      },
      {
        "timestamp": "0:39-0:41",
        "type": "content",
        "description": "She explicitly mentions the app: 'That's why fluently works.'",
        "textOnScreen": "That's why fluently works.",
        "spokenWords": "That's why fluently works.",
        "transition": "cut",
        "cameraAngle": "medium",
        "emotionalBeat": "Direct product introduction."
      },
      {
        "timestamp": "0:41-0:44",
        "type": "content",
        "description": "She describes the app: 'It's like a speaking partner in your pocket.'",
        "textOnScreen": "It's like a speaking partner in your pocket.",
        "spokenWords": "It's like a speaking partner in your pocket.",
        "transition": "cut",
        "cameraAngle": "medium",
        "emotionalBeat": "Benefit-oriented description, convenience."
      },
      {
        "timestamp": "0:44-0:46",
        "type": "cta",
        "description": "A strong call to action: 'Stop learning English.'",
        "textOnScreen": "Stop learning English.",
        "spokenWords": "Stop learning English.",
        "transition": "cut",
        "cameraAngle": "medium",
        "emotionalBeat": "Urgency, paradigm shift."
      },
      {
        "timestamp": "0:46-0:49",
        "type": "cta",
        "description": "The final call to action: 'Start speaking with fluently app.' The app logo appears on screen.",
        "textOnScreen": "Start speaking with fluently app.",
        "spokenWords": "Start speaking with fluently app.",
        "transition": "cut",
        "cameraAngle": "medium",
        "emotionalBeat": "Clear instruction, direct action."
      }
    ],
    "editing": {
      "pace": "fast",
      "averageCutLength": "2-3 seconds for the homograph section, then 2-5 seconds for the explanation/CTA",
      "transitions": [
        "cut"
      ],
      "effects": [
        "text overlays appearing dynamically"
      ],
      "textOverlays": {
        "style": "Clean, sans-serif font.",
        "font": "Arial or similar sans-serif",
        "colors": [
          "white",
          "black (outline)"
        ],
        "animation": "Appears instantly or fades in quickly.",
        "position": "Centered below the images for homographs, then across the screen for the main message."
      },
      "colorGrading": "neutral"
    },
    "audio": {
      "hasVoiceover": false,
      "hasSpeech": true,
      "hasSinging": false,
      "hasMusic": false,
      "musicDetails": "N/A",
      "voiceTone": "Clear, articulate, confident, and engaging. Initially instructional, then persuasive.",
      "audioStructure": "Speech only, with clear pronunciation and emphasis.",
      "soundEffects": []
    },
    "viralFactors": {
      "primaryViralMechanic": "Problem-solution framework combined with a relatable linguistic challenge.",
      "whyItWorks": "The initial rapid-fire presentation of homographs is a highly engaging pattern interrupt that immediately resonates with anyone who has tried to learn English, creating a sense of 'I know this struggle!' or 'This is interesting!'. This recognition triggers an emotional connection. The video then directly addresses a common frustration (the perceived need for endless vocabulary) and offers a clear, modern solution (AI speaking practice) via a specific product. This combination of relatable problem, debunking a myth, and offering a practical, accessible solution makes it highly shareable among English learners.",
      "targetAudience": "English language learners (ESL/EFL students), individuals interested in language acquisition, people looking for self-improvement tools, users of AI-powered educational apps. Demographics likely skew younger (18-35) given the platform.",
      "emotionalTrigger": "Recognition, frustration (with language learning), hope, curiosity, empowerment.",
      "shareability": "high - people will share this with friends also learning English, or with teachers, or simply because they found the homograph challenge interesting and relatable.",
      "commentBait": "People will comment on which homographs they find most difficult, share their own language learning struggles, or ask for more details about the app.",
      "retentionTechniques": [
        "Fast pace in the hook",
        "Direct address to the camera",
        "Clear, concise messaging",
        "Problem-solution narrative",
        "Dynamic text overlays"
      ],
      "platformOptimization": "Short, vertical format suitable for Reels/Shorts/TikTok. Engaging hook within the first 3 seconds. Clear call to action. Relatable content for a broad audience (language learners)."
    },
    "reproductionGuide": {
      "difficulty": "easy",
      "conceptCore": "Engage viewers with a relatable challenge, debunk a common misconception, then introduce a product as the effective solution.",
      "requiredAssets": [
        "Creator speaking to camera",
        "Images related to the challenge (e.g., homographs, common misconceptions)",
        "Text overlay capability",
        "A product/service to promote"
      ],
      "steps": [
        "Identify a common, relatable challenge or misconception within your niche (e.g., fitness, cooking, tech).",
        "Create a fast-paced, visually engaging hook demonstrating this challenge or misconception (e.g., quick examples, common mistakes).",
        "Directly address the camera and state the 'biggest lie' or 'common mistake' related to the challenge.",
        "Immediately pivot to the true solution or what people 'really need'.",
        "Introduce your product/service as the ideal tool to achieve this solution.",
        "Provide a clear, benefit-driven description of your product.",
        "End with a strong, concise call to action to use your product."
      ],
      "variationIdeas": [
        "Fitness: 'The biggest lie about getting fit? You need to spend hours in the gym. You don't. You need consistent, short bursts of activity. That's why [App Name] works. It's like a personal trainer for 15-minute workouts.'",
        "Cooking: 'The biggest lie about cooking healthy? It takes too much time. It doesn't. You need simple, quick recipes. That's why [Recipe Book/App Name] works. It's like a meal planner in your pocket.'",
        "Productivity: 'The biggest lie about being productive? You need to multitask. You don't. You need focused, single-task blocks. That's why [App Name] works. It's like a focus coach for your workday.'",
        "Finance: 'The biggest lie about saving money? You need a huge income. You don't. You need smart budgeting and tracking. That's why [App Name] works. It's like a financial advisor in your pocket.'"
      ],
      "whatToAvoid": [
        "Making the hook too long or slow.",
        "Being vague about the problem or solution.",
        "Not clearly articulating the product's benefit.",
        "A weak or unclear call to action.",
        "Overly complex visuals that distract from the message."
      ]
    }
  }
}